covid19_data/__init__.py
covid19_data/dict_as_attribute.py
covid19_data/JHU/__init__.py
covid19_data/JHU/get_data.py
covid19_data/JHU/get_object.py
tests/__init__.py
tests/test_attribute_style.py
tests/test_get_data.py
tests/test_get_object.py
tests/test_main.py
covid19_data-1.2.0.dist-info/LICENSE
covid19_data-1.2.0.dist-info/METADATA
covid19_data-1.2.0.dist-info/WHEEL
covid19_data-1.2.0.dist-info/top_level.txt
covid19_data-1.2.0.dist-info/RECORD
