Metadata-Version: 2.1
Name: covid19-data
Version: 1.2.0
Summary: A fast, powerful, and flexible way to get up to date COVID-19 data for any major city, state, country, and total world wide data, with just one line of code
Home-page: http://github.com/binarynightowl/covid19_python
Author: Taylor Dettling
Author-email: taylor@binarynightowl.com
License: MIT
Keywords: covid covid-19 corona coronavirus query hopkins python attribute fast easy powerful flexible json data statistics city state total world john hopkins scraping
Platform: UNKNOWN
Classifier: Intended Audience :: Developers
Classifier: Topic :: Software Development
Classifier: Development Status :: 5 - Production/Stable
Classifier: Programming Language :: Python :: 3
Classifier: Operating System :: OS Independent
Requires-Python: >=3
